{"tittle":"Maestros del Magic","proposal":"Sumérgete en el fascinante mundo de Magic: The Gathering y descubre las estrategias de los maestros . A través de preguntas intrigantes aprenderás sobre los formatos de juego, las tácticas y la historia del juego, mientras te diviertes y compites con tus amigos.","autor":"elmundoesazul@gmail.com ","imageURL":"","questionsCount":30,"challengesCount":0,"tiles":[{"id":0,"type":"Start","challenge":{"description":""},"question":{"statement":"","options":[],"correctId":0}},{"id":1,"type":"TravelToTile","challenge":{"description":""},"question":{"statement":"","options":[],"correctId":0}},{"id":2,"type":"RollDicesAgain","challenge":{"description":""},"question":{"statement":"","options":[],"correctId":0}},{"id":3,"type":"Question","challenge":{"description":""},"question":{"statement":"¿Qué habilidad permite a una criatura atacar sin ser bloqueada?","options":["Prisa","Vigilancia","Destello","Toque mortal"],"correctId":0}},{"id":4,"type":"Question","challenge":{"description":""},"question":{"statement":"¿Cuál es el término que se utiliza para describir a un jugador que utiliza un mazo muy poderoso?","options":["Competitivo","Casual","Estratega","Maestro"],"correctId":0}},{"id":5,"type":"Question","challenge":{"description":""},"question":{"statement":"¿Qué habilidad de las criaturas permite a los jugadores sacrificarla para activar efectos?","options":["Sacrificio","Exilio","Destello","Vigilancia"],"correctId":0}},{"id":6,"type":"LoseTurnsUntil","challenge":{"description":""},"question":{"statement":"","options":[],"correctId":0}},{"id":7,"type":"TravelToTile","challenge":{"description":""},"question":{"statement":"","options":[],"correctId":0}},{"id":8,"type":"Question","challenge":{"description":""},"question":{"statement":"¿Cuál es el término que se utiliza para describir a un jugador que juega de manera muy agresiva?","options":["Ofensivo","Defensivo","Estratega","Maestro"],"correctId":0}},{"id":9,"type":"Question","challenge":{"description":""},"question":{"statement":"¿Cuál es el término que describe el costo adicional que se paga para lanzar un hechizo?","options":["Costo de maná","Costo de vida","Costo de sacrificio","Costo de exilio"],"correctId":0}},{"id":10,"type":"RollDicesAgain","challenge":{"description":""},"question":{"statement":"","options":[],"correctId":0}},{"id":11,"type":"Question","challenge":{"description":""},"question":{"statement":"¿Qué formato de juego se basa en un mazo de 40 cartas y se juega en un entorno limitado?","options":["Commander","Draft","Sellado","Pauper"],"correctId":1}},{"id":12,"type":"Question","challenge":{"description":""},"question":{"statement":"¿Cuál es el efecto de la habilidad de 'Destello'?","options":["Jugar en el turno del oponente","Aumentar el poder","Robar cartas","Destruir criaturas"],"correctId":0}},{"id":13,"type":"TravelToTile","challenge":{"description":""},"question":{"statement":"","options":[],"correctId":0}},{"id":14,"type":"Question","challenge":{"description":""},"question":{"statement":"¿Qué carta permite a un jugador buscar en su mazo una carta específica y ponerla en su mano?","options":["Búsqueda","Scry","Tutoreo","Revelación"],"correctId":2}},{"id":15,"type":"Challenge","challenge":{"description":"Comparte con los demás cual es tu color favorito y porque."},"question":{"statement":"¿Qué tipo de carta se utiliza para dar habilidades adicionales a las criaturas?","options":["Encantamiento","Hechizo","Artefacto","Criatura"],"correctId":0}},{"id":16,"type":"Challenge","challenge":{"description":"Explica cual es para ti la carta más poderosa del juego."},"question":{"statement":"","options":[],"correctId":0}},{"id":17,"type":"RollDicesAgain","challenge":{"description":""},"question":{"statement":"","options":[],"correctId":0}},{"id":18,"type":"LoseTurnsUntil","challenge":{"description":""},"question":{"statement":"","options":[],"correctId":0}},{"id":19,"type":"Question","challenge":{"description":""},"question":{"statement":"¿Cuál es la habilidad que permite a una criatura atacar y bloquear en el mismo turno?","options":["Prisa","Vigilancia","Destello","Toque mortal"],"correctId":1}},{"id":20,"type":"Bridge","challenge":{"description":""},"question":{"statement":"","options":[],"correctId":0}},{"id":21,"type":"TravelToTile","challenge":{"description":""},"question":{"statement":"","options":[],"correctId":0}},{"id":22,"type":"LoseTurnsUntil","challenge":{"description":""},"question":{"statement":"","options":[],"correctId":0}},{"id":23,"type":"Question","challenge":{"description":""},"question":{"statement":"¿Qué color de maná se asocia con la naturaleza y el crecimiento de criaturas?","options":["Negro","Verde","Rojo","Azul"],"correctId":1}},{"id":24,"type":"RollDicesAgain","challenge":{"description":""},"question":{"statement":"","options":[],"correctId":0}},{"id":25,"type":"TravelToTile","challenge":{"description":""},"question":{"statement":"","options":[],"correctId":0}},{"id":26,"type":"Question","challenge":{"description":""},"question":{"statement":"¿Qué color de maná se asocia comúnmente con la manipulación de la mente y el control de criaturas?","options":["Rojo","Verde","Azul","Negro"],"correctId":2}},{"id":27,"type":"LoseTurnsUntil","challenge":{"description":""},"question":{"statement":"","options":[],"correctId":0}},{"id":28,"type":"Question","challenge":{"description":""},"question":{"statement":"¿Qué tipo de carta permite a los jugadores robar cartas adicionales en su turno?","options":["Encantamiento","Criatura","Instantáneo","Hechizo"],"correctId":1}},{"id":29,"type":"RollDicesAgain","challenge":{"description":""},"question":{"statement":"","options":[],"correctId":0}},{"id":30,"type":"LoseTurnsUntil","challenge":{"description":""},"question":{"statement":"","options":[],"correctId":0}},{"id":31,"type":"Question","challenge":{"description":""},"question":{"statement":"¿Qué tipo de carta se utiliza para dar habilidades adicionales a las criaturas?","options":["Encantamiento","Hechizo","Artefacto","Criatura"],"correctId":0}},{"id":32,"type":"Question","challenge":{"description":""},"question":{"statement":"¿Qué carta permite a un jugador robar cartas hasta que tenga siete en su mano?","options":["Robo de cartas","Recuperación","Revelación","Suerte"],"correctId":2}},{"id":33,"type":"TravelToTile","challenge":{"description":""},"question":{"statement":"","options":[],"correctId":0}},{"id":34,"type":"LoseTurnsUntil","challenge":{"description":""},"question":{"statement":"","options":[],"correctId":0}},{"id":35,"type":"Bridge","challenge":{"description":""},"question":{"statement":"","options":[],"correctId":0}},{"id":36,"type":"Question","challenge":{"description":""},"question":{"statement":"¿Cuál es el término que describe el proceso de mezclar cartas en un mazo?","options":["Barajar","Ordenar","Clasificar","Reorganizar"],"correctId":0}},{"id":37,"type":"Die","challenge":{"description":""},"question":{"statement":"¿Cuál es el término que describe el proceso de mezclar cartas en un mazo?","options":["Barajar","Ordenar","Clasificar","Reorganizar"],"correctId":0}},{"id":38,"type":"Question","challenge":{"description":""},"question":{"statement":"¿Qué carta es conocida por su capacidad de devolver criaturas del cementerio a la mano?","options":["Resurrección","Revitalizar","Reanimar","Regenerar"],"correctId":0}},{"id":39,"type":"End","challenge":{"description":""},"question":{"statement":"","options":[],"correctId":0}}],"challengeTypes":["Escribir","Dibujar","Decir","Hacer"],"_serializedQuestions":[{"statement":"¿Qué carta es famosa por su habilidad de hacer que el oponente pierda vida cada vez que se juega un hechizo?","options":["Sanguinario","Nefarious","Héroe de la batalla","Cazador de almas"],"correctId":1},{"statement":"¿Cuál es el término que se utiliza para describir a un jugador que juega de manera muy defensiva?","options":["Ofensivo","Defensivo","Agresivo","Estratégico"],"correctId":1},{"statement":"¿Cuál de las siguientes cartas es conocida por su capacidad de destruir permanentes?","options":["Rayo","Destrucción de criaturas","Fuerza de la naturaleza","Desintegrar"],"correctId":3},{"statement":"¿Qué tipo de carta puede ser jugada en cualquier momento, incluso en el turno del oponente?","options":["Hechizo","Instantáneo","Criatura","Encantamiento"],"correctId":1},{"statement":"¿Qué habilidad permite a una criatura atacar sin ser bloqueada?","options":["Vigilancia","Prisa","Destello","Toque mortal"],"correctId":2},{"statement":"¿Qué carta es famosa por su habilidad de hacer que el oponente descarte cartas?","options":["Descarte","Despojo","Robo","Sustracción"],"correctId":1},{"statement":"¿Cuál es el formato de juego que permite a los jugadores construir mazos con cartas de cualquier expansión?","options":["Commander","Standard","Modern","Legacy"],"correctId":0},{"statement":"¿Qué habilidad permite a un jugador jugar cartas de su cementerio?","options":["Recuperación","Reanimar","Resurrección","Exilio"],"correctId":1},{"statement":"¿Qué tipo de carta se utiliza para aumentar el poder de las criaturas en el campo de batalla?","options":["Encantamiento","Artefacto","Hechizo","Criatura"],"correctId":0},{"statement":"¿Qué habilidad permite a una criatura evitar ser destruida por daño?","options":["Indestructible","Inmortal","Invisibilidad","Protección"],"correctId":0},{"statement":"¿Qué tipo de carta se utiliza para aumentar la cantidad de maná disponible?","options":["Artefacto","Encantamiento","Hechizo","Criatura"],"correctId":0},{"statement":"¿Cuál es la habilidad que permite a una criatura infligir daño a la criatura o jugador objetivo?","options":["Toque mortal","Prisa","Daño de combate","Destello"],"correctId":0},{"statement":"¿Cuál es el objetivo principal del juego Magic: The Gathering?","options":["Reducir la vida del oponente a cero","Robar todas las cartas","Controlar el campo de batalla","Crear el mazo más grande"],"correctId":0}],"_serializedChallenges":["Explica como recuerdas tus inicios en el magic, que carta te viene a la memoria de esa época?"]}
